flickr_photostream_sorter
