Metadata-Version: 1.1
Name: flickr-photostream-sorter
Version: 0.1.1
Summary: Sort your Flickr photostream by changing each photo's posted date to when it was taken.
Home-page: https://github.com/jschementi/flickr_photostream_sorter
Author: Jimmy Schementi
Author-email: jimmy@schementi.com
License: UNKNOWN
Keywords: flickr photostream sort
Platform: UNKNOWN
Classifier: Development Status :: 4 - Beta
Classifier: Environment :: Console
Classifier: Intended Audience :: End Users/Desktop
Classifier: License :: OSI Approved :: MIT License
Classifier: Natural Language :: English
Classifier: Operating System :: POSIX :: Linux
Classifier: Operating System :: MacOS :: MacOS X
Classifier: Programming Language :: Python :: 2.7
Classifier: Topic :: Utilities
